Encrypt_decrypt_tfi/__init__.py
File_manipulation/__init__.py
Encrypt_decrypt_tfi-1.0.dist-info/LICENSE.txt
Encrypt_decrypt_tfi-1.0.dist-info/METADATA
Encrypt_decrypt_tfi-1.0.dist-info/WHEEL
Encrypt_decrypt_tfi-1.0.dist-info/top_level.txt
Encrypt_decrypt_tfi-1.0.dist-info/RECORD
