Metadata-Version: 2.1
Name: Encrypt-decrypt-tfi
Version: 1.0
Summary: A package for encrypting and decrypting text and image files
Author: Wahid Hussain
Author-email: wahidhussain643@gmail.com
License: MIT
Classifier: Development Status :: 3 - Alpha
Classifier: Intended Audience :: Developers
Classifier: License :: OSI Approved :: MIT License
Classifier: Programming Language :: Python :: 3
Classifier: Programming Language :: Python :: 3.6
Classifier: Programming Language :: Python :: 3.7
Classifier: Programming Language :: Python :: 3.8
Classifier: Programming Language :: Python :: 3.9
License-File: LICENSE.txt
